DoubleLinkedList/DLinked.py
DoubleLinkedList/__init__.py
DoubleLinkedList-1.0.4.dist-info/LICENSE
DoubleLinkedList-1.0.4.dist-info/METADATA
DoubleLinkedList-1.0.4.dist-info/WHEEL
DoubleLinkedList-1.0.4.dist-info/top_level.txt
DoubleLinkedList-1.0.4.dist-info/RECORD
