Metadata-Version: 2.1
Name: DoubleLinkedList
Version: 1.0.4
Summary: This package is double linked list
Home-page: https://github.com/Timofey-Ivantsov
Author: Ivantsov Timofey
Author-email: TimofeyIvantsov@yandex.ru
License: UNKNOWN
Project-URL: Bug Tracker, https://github.com/pypa/sampleproject/issues
Platform: UNKNOWN
Classifier: Programming Language :: Python :: 3
Classifier: License :: OSI Approved :: MIT License
Classifier: Operating System :: OS Independent
Requires-Python: >=3.0
